lsq_solver/__about__.py
lsq_solver/__init__.py
lsq_solver/_residual_block.py
lsq_solver/auto_diff.py
lsq_solver/loss_funcs.py
lsq_solver/problem.py
lsq_solver/rotation.py
lsq_solver-0.3.1.dist-info/METADATA
lsq_solver-0.3.1.dist-info/WHEEL
lsq_solver-0.3.1.dist-info/licenses/LICENSE
lsq_solver-0.3.1.dist-info/RECORD
