Metadata-Version: 2.1
Name: lsq-solver
Version: 0.3.1
Project-URL: Documentation, https://github.com/powei-lin/lsq-solver#readme
Project-URL: Issues, https://github.com/powei-lin/lsq-solver/issues
Project-URL: Source, https://github.com/powei-lin/lsq-solver
Author-email: Powei Lin <poweilin1994@gmail.com>, Jerry Zhao <jerry.zy@foxmail.com>
License-Expression: MIT
License-File: LICENSE
Classifier: Development Status :: 4 - Beta
Classifier: Programming Language :: Python
Classifier: Programming Language :: Python :: 3.7
Classifier: Programming Language :: Python :: 3.8
Classifier: Programming Language :: Python :: 3.9
Classifier: Programming Language :: Python :: 3.10
Classifier: Programming Language :: Python :: 3.11
Classifier: Programming Language :: Python :: Implementation :: CPython
Classifier: Programming Language :: Python :: Implementation :: PyPy
Requires-Python: >=3.7
Requires-Dist: scipy
Provides-Extra: dual
Requires-Dist: num-dual; extra == 'dual'
Provides-Extra: features
Requires-Dist: dual; extra == 'features'
